{
	"name": "Babe Plataformer",
	"displayWidth": 800,
	"displayHeight": 480,
	"cameraX": 0,
	"cameraY": 0,
	"cameraAngle": 0,
	"cameraZoom": 1,
	"backgroundColor": "#ffffff",
	"soundOn": false,
	"soundtrack": "",
	"volume": 1,
	"start": 0,
	"pan": 0,
	"loop": false,
	"physicsOn": false,
	"gravityX": 0,
	"gravityY": -9.8,
	"tagList": [
		"player",
		"floor",
		"enemy"
	],
	"sceneList": [
		{
			"name": "Scene_1",
			"actorList": [
				{
					"name": "background",
					"sleeping": false,
					"x": 3.784218811039864,
					"y": 0.946054702759966,
					"width": 1000,
					"height": 750,
					"scaleX": 1,
					"scaleY": 1,
					"angle": 0,
					"screen": true,
					"collider": "Box",
					"tags": "",
					"spriteOn": true,
					"image": "BG1.png",
					"color": "#ffffff",
					"opacity": 1,
					"flipX": false,
					"flipY": false,
					"scrollX": 0,
					"scrollY": 0,
					"tileX": 1,
					"tileY": 1,
					"textOn": false,
					"text": "",
					"font": "Arial",
					"size": 30,
					"fill": "#000000",
					"style": "Normal",
					"align": "Center",
					"offsetX": 0,
					"offsetY": 0,
					"soundOn": false,
					"sound": "",
					"start": 0,
					"volume": 1,
					"pan": 0,
					"loop": false,
					"physicsOn": false,
					"type": "Dynamic",
					"fixedAngle": false,
					"velocityX": 0,
					"velocityY": 0,
					"angularVelocity": 0,
					"density": 1,
					"friction": 0.5,
					"restitution": 0.5,
					"dampingLinear": 0,
					"dampingAngular": 0,
					"scriptList": []
				},
				{
					"name": "Player",
					"sleeping": false,
					"x": -263.5926079690877,
					"y": -14.392732104396373,
					"width": 66,
					"height": 80,
					"scaleX": 0.5,
					"scaleY": 0.4968944099378882,
					"angle": 0,
					"screen": false,
					"collider": "Box",
					"tags": "player",
					"spriteOn": true,
					"image": "Purple_Front1.png",
					"color": "#ffffff",
					"opacity": 1,
					"flipX": false,
					"flipY": false,
					"scrollX": 0,
					"scrollY": 0,
					"tileX": 1,
					"tileY": 1,
					"textOn": true,
					"text": "",
					"font": "Arial",
					"size": 30,
					"fill": "#000000",
					"style": "Normal",
					"align": "Center",
					"offsetX": 0,
					"offsetY": 0,
					"soundOn": false,
					"sound": "",
					"start": 0,
					"volume": 1,
					"pan": 0,
					"loop": false,
					"physicsOn": true,
					"type": "Dynamic",
					"fixedAngle": true,
					"velocityX": 0,
					"velocityY": 0,
					"angularVelocity": 0,
					"density": 1,
					"friction": 0.5,
					"restitution": 0,
					"dampingLinear": 0,
					"dampingAngular": 0,
					"scriptList": [
						{
							"name": "movement",
							"nodeList": [
								{
									"type": "Keyboard",
									"parameters": {
										"key": "ArrowRight",
										"key_Mode": "Pressed"
									},
									"nodeListTrue": [
										{
											"type": "Edit",
											"parameters": {
												"property": "Me.flipX",
												"value": false
											}
										},
										{
											"type": "Animate",
											"parameters": {
												"animation": "Purple_Right1.png,Purple_Right2.png,Purple_Right3.png",
												"fps": 24
											}
										},
										{
											"type": "Move",
											"parameters": {
												"speed": "300",
												"angle": 0
											}
										}
									],
									"nodeListFalse": []
								},
								{
									"type": "Keyboard",
									"parameters": {
										"key": "ArrowLeft",
										"key_Mode": "Pressed"
									},
									"nodeListTrue": [
										{
											"type": "Animate",
											"parameters": {
												"animation": "Purple_Right1.png,Purple_Right2.png,Purple_Right3.png",
												"fps": 24
											}
										},
										{
											"type": "Edit",
											"parameters": {
												"property": "Me.flipX",
												"value": true
											}
										},
										{
											"type": "Move",
											"parameters": {
												"speed": "-300",
												"angle": 0
											}
										}
									],
									"nodeListFalse": []
								},
								{
									"type": "Keyboard",
									"parameters": {
										"key": "ArrowUp",
										"key_Mode": "Down"
									},
									"nodeListTrue": [
										{
											"type": "Collision",
											"parameters": {
												"tags": "floor"
											},
											"nodeListTrue": [
												{
													"type": "Push",
													"parameters": {
														"force": "30",
														"angle": "90"
													}
												}
											],
											"nodeListFalse": []
										}
									],
									"nodeListFalse": []
								}
							]
						},
						{
							"name": "camera",
							"nodeList": [
								{
									"type": "Compare",
									"parameters": {
										"value_1": "Me.x",
										"operation": "Greater",
										"value_2": "0"
									},
									"nodeListTrue": [
										{
											"type": "Edit",
											"parameters": {
												"property": "Game.cameraX",
												"value": "Me.x"
											}
										}
									],
									"nodeListFalse": []
								}
							]
						},
						{
							"name": "dead",
							"nodeList": [
								{
									"type": "Collision",
									"parameters": {
										"tags": "enemy"
									},
									"nodeListTrue": [],
									"nodeListFalse": []
								}
							]
						}
					]
				},
				{
					"name": "Actor_2",
					"sleeping": false,
					"x": -241,
					"y": -208,
					"width": 320,
					"height": 64,
					"scaleX": 1,
					"scaleY": 1,
					"angle": 0,
					"screen": false,
					"collider": "Box",
					"tags": "floor",
					"spriteOn": true,
					"image": "ZigzagGrass_Squar.png",
					"color": "#ffffff",
					"opacity": 1,
					"flipX": false,
					"flipY": false,
					"scrollX": 0,
					"scrollY": 0,
					"tileX": 5,
					"tileY": 1,
					"textOn": false,
					"text": "",
					"font": "Arial",
					"size": 30,
					"fill": "#000000",
					"style": "Normal",
					"align": "Center",
					"offsetX": 0,
					"offsetY": 0,
					"soundOn": false,
					"sound": "",
					"start": 0,
					"volume": 1,
					"pan": 0,
					"loop": false,
					"physicsOn": true,
					"type": "Static",
					"fixedAngle": false,
					"velocityX": 0,
					"velocityY": 0,
					"angularVelocity": 0,
					"density": 1,
					"friction": 0.5,
					"restitution": 0,
					"dampingLinear": 0,
					"dampingAngular": 0,
					"scriptList": []
				},
				{
					"name": "Actor_2_copy",
					"sleeping": false,
					"x": 214,
					"y": -208,
					"width": 320,
					"height": 64,
					"scaleX": 1,
					"scaleY": 1,
					"angle": 0,
					"screen": false,
					"collider": "Box",
					"tags": "floor",
					"spriteOn": true,
					"image": "ZigzagGrass_Squar.png",
					"color": "#ffffff",
					"opacity": 1,
					"flipX": false,
					"flipY": false,
					"scrollX": 0,
					"scrollY": 0,
					"tileX": 5,
					"tileY": 1,
					"textOn": false,
					"text": "",
					"font": "Arial",
					"size": 30,
					"fill": "#000000",
					"style": "Normal",
					"align": "Center",
					"offsetX": 0,
					"offsetY": 0,
					"soundOn": false,
					"sound": "",
					"start": 0,
					"volume": 1,
					"pan": 0,
					"loop": false,
					"physicsOn": true,
					"type": "Static",
					"fixedAngle": false,
					"velocityX": 0,
					"velocityY": 0,
					"angularVelocity": 0,
					"density": 1,
					"friction": 0.5,
					"restitution": 0,
					"dampingLinear": 0,
					"dampingAngular": 0,
					"scriptList": []
				},
				{
					"name": "Actor_2_copy_2",
					"sleeping": false,
					"x": 688,
					"y": -208,
					"width": 320,
					"height": 64,
					"scaleX": 1,
					"scaleY": 1,
					"angle": 0,
					"screen": false,
					"collider": "Box",
					"tags": "floor",
					"spriteOn": true,
					"image": "ZigzagGrass_Squar.png",
					"color": "#ffffff",
					"opacity": 1,
					"flipX": false,
					"flipY": false,
					"scrollX": 0,
					"scrollY": 0,
					"tileX": 5,
					"tileY": 1,
					"textOn": false,
					"text": "",
					"font": "Arial",
					"size": 30,
					"fill": "#000000",
					"style": "Normal",
					"align": "Center",
					"offsetX": 0,
					"offsetY": 0,
					"soundOn": false,
					"sound": "",
					"start": 0,
					"volume": 1,
					"pan": 0,
					"loop": false,
					"physicsOn": true,
					"type": "Static",
					"fixedAngle": false,
					"velocityX": 0,
					"velocityY": 0,
					"angularVelocity": 0,
					"density": 1,
					"friction": 0.5,
					"restitution": 0,
					"dampingLinear": 0,
					"dampingAngular": 0,
					"scriptList": []
				},
				{
					"name": "wall",
					"sleeping": false,
					"x": -427.34851977850343,
					"y": 0.27502697163552625,
					"width": 50,
					"height": 479.39911358165676,
					"scaleX": 1,
					"scaleY": 9.587982271633136,
					"angle": 0,
					"screen": false,
					"collider": "Box",
					"tags": "",
					"spriteOn": false,
					"image": "",
					"color": "#ffffff",
					"opacity": 1,
					"flipX": false,
					"flipY": false,
					"scrollX": 0,
					"scrollY": 0,
					"tileX": 1,
					"tileY": 1,
					"textOn": false,
					"text": "",
					"font": "Arial",
					"size": 30,
					"fill": "#000000",
					"style": "Normal",
					"align": "Center",
					"offsetX": 0,
					"offsetY": 0,
					"soundOn": false,
					"sound": "",
					"start": 0,
					"volume": 1,
					"pan": 0,
					"loop": false,
					"physicsOn": true,
					"type": "Static",
					"fixedAngle": false,
					"velocityX": 0,
					"velocityY": 0,
					"angularVelocity": 0,
					"density": 1,
					"friction": 0.5,
					"restitution": 0.5,
					"dampingLinear": 0,
					"dampingAngular": 0,
					"scriptList": []
				},
				{
					"name": "coinsControler",
					"sleeping": false,
					"x": 319.0629481338598,
					"y": 200,
					"width": 60.50168323527725,
					"height": 50,
					"scaleX": 1.210033664705545,
					"scaleY": 1,
					"angle": 0,
					"screen": true,
					"collider": "Box",
					"tags": "",
					"spriteOn": false,
					"image": "",
					"color": "#ffffff",
					"opacity": 1,
					"flipX": false,
					"flipY": false,
					"scrollX": 0,
					"scrollY": 0,
					"tileX": 1,
					"tileY": 1,
					"textOn": true,
					"text": "${Me.coins}",
					"font": "Tahoma",
					"size": 20,
					"fill": "#d8af52",
					"style": "Bold",
					"align": "Right",
					"offsetX": 0,
					"offsetY": 0,
					"soundOn": false,
					"sound": "",
					"start": 0,
					"volume": 1,
					"pan": 0,
					"loop": false,
					"physicsOn": false,
					"type": "Dynamic",
					"fixedAngle": false,
					"velocityX": 0,
					"velocityY": 0,
					"angularVelocity": 0,
					"density": 1,
					"friction": 0.5,
					"restitution": 0.5,
					"dampingLinear": 0,
					"dampingAngular": 0,
					"scriptList": [
						{
							"name": "Script_1",
							"nodeList": []
						}
					],
					"coins": 0
				},
				{
					"name": "coin",
					"sleeping": false,
					"x": 168,
					"y": -133,
					"width": 21,
					"height": 21,
					"scaleX": 1,
					"scaleY": 1,
					"angle": 0,
					"screen": false,
					"collider": "Box",
					"tags": "",
					"spriteOn": true,
					"image": "CoinYellow.png",
					"color": "#ffffff",
					"opacity": 1,
					"flipX": false,
					"flipY": false,
					"scrollX": 0,
					"scrollY": 0,
					"tileX": 1,
					"tileY": 1,
					"textOn": false,
					"text": "",
					"font": "Arial",
					"size": 30,
					"fill": "#000000",
					"style": "Normal",
					"align": "Center",
					"offsetX": 0,
					"offsetY": 0,
					"soundOn": false,
					"sound": "",
					"start": 0,
					"volume": 1,
					"pan": 0,
					"loop": false,
					"physicsOn": false,
					"type": "Dynamic",
					"fixedAngle": false,
					"velocityX": 0,
					"velocityY": 0,
					"angularVelocity": 0,
					"density": 1,
					"friction": 0.5,
					"restitution": 0.5,
					"dampingLinear": 0,
					"dampingAngular": 0,
					"scriptList": [
						{
							"name": "Script_1",
							"nodeList": [
								{
									"type": "Collision",
									"parameters": {
										"tags": "player"
									},
									"nodeListTrue": [
										{
											"type": "Edit",
											"parameters": {
												"property": "coinsControler.coins",
												"value": "coinsControler.coins+1"
											}
										},
										{
											"type": "Delete",
											"parameters": {}
										}
									],
									"nodeListFalse": []
								}
							]
						}
					]
				},
				{
					"name": "coin_copy_3",
					"sleeping": false,
					"x": 742,
					"y": -133,
					"width": 21,
					"height": 21,
					"scaleX": 1,
					"scaleY": 1,
					"angle": 0,
					"screen": false,
					"collider": "Box",
					"tags": "",
					"spriteOn": true,
					"image": "CoinYellow.png",
					"color": "#ffffff",
					"opacity": 1,
					"flipX": false,
					"flipY": false,
					"scrollX": 0,
					"scrollY": 0,
					"tileX": 1,
					"tileY": 1,
					"textOn": false,
					"text": "",
					"font": "Arial",
					"size": 30,
					"fill": "#000000",
					"style": "Normal",
					"align": "Center",
					"offsetX": 0,
					"offsetY": 0,
					"soundOn": false,
					"sound": "",
					"start": 0,
					"volume": 1,
					"pan": 0,
					"loop": false,
					"physicsOn": false,
					"type": "Dynamic",
					"fixedAngle": false,
					"velocityX": 0,
					"velocityY": 0,
					"angularVelocity": 0,
					"density": 1,
					"friction": 0.5,
					"restitution": 0.5,
					"dampingLinear": 0,
					"dampingAngular": 0,
					"scriptList": [
						{
							"name": "Script_1",
							"nodeList": [
								{
									"type": "Collision",
									"parameters": {
										"tags": "player"
									},
									"nodeListTrue": [
										{
											"type": "Edit",
											"parameters": {
												"property": "coinsControler.coins",
												"value": "coinsControler.coins+1"
											}
										},
										{
											"type": "Delete",
											"parameters": {}
										}
									],
									"nodeListFalse": []
								}
							]
						}
					]
				},
				{
					"name": "coin_copy_2",
					"sleeping": false,
					"x": 586,
					"y": -133,
					"width": 21,
					"height": 21,
					"scaleX": 1,
					"scaleY": 1,
					"angle": 0,
					"screen": false,
					"collider": "Box",
					"tags": "",
					"spriteOn": true,
					"image": "CoinYellow.png",
					"color": "#ffffff",
					"opacity": 1,
					"flipX": false,
					"flipY": false,
					"scrollX": 0,
					"scrollY": 0,
					"tileX": 1,
					"tileY": 1,
					"textOn": false,
					"text": "",
					"font": "Arial",
					"size": 30,
					"fill": "#000000",
					"style": "Normal",
					"align": "Center",
					"offsetX": 0,
					"offsetY": 0,
					"soundOn": false,
					"sound": "",
					"start": 0,
					"volume": 1,
					"pan": 0,
					"loop": false,
					"physicsOn": false,
					"type": "Dynamic",
					"fixedAngle": false,
					"velocityX": 0,
					"velocityY": 0,
					"angularVelocity": 0,
					"density": 1,
					"friction": 0.5,
					"restitution": 0.5,
					"dampingLinear": 0,
					"dampingAngular": 0,
					"scriptList": [
						{
							"name": "Script_1",
							"nodeList": [
								{
									"type": "Collision",
									"parameters": {
										"tags": "player"
									},
									"nodeListTrue": [
										{
											"type": "Edit",
											"parameters": {
												"property": "coinsControler.coins",
												"value": "coinsControler.coins+1"
											}
										},
										{
											"type": "Delete",
											"parameters": {}
										}
									],
									"nodeListFalse": []
								}
							]
						}
					]
				},
				{
					"name": "coin_copy",
					"sleeping": false,
					"x": 288.2772051992318,
					"y": -133,
					"width": 21,
					"height": 21,
					"scaleX": 1,
					"scaleY": 1,
					"angle": 0,
					"screen": false,
					"collider": "Box",
					"tags": "",
					"spriteOn": true,
					"image": "CoinYellow.png",
					"color": "#ffffff",
					"opacity": 1,
					"flipX": false,
					"flipY": false,
					"scrollX": 0,
					"scrollY": 0,
					"tileX": 1,
					"tileY": 1,
					"textOn": false,
					"text": "",
					"font": "Arial",
					"size": 30,
					"fill": "#000000",
					"style": "Normal",
					"align": "Center",
					"offsetX": 0,
					"offsetY": 0,
					"soundOn": false,
					"sound": "",
					"start": 0,
					"volume": 1,
					"pan": 0,
					"loop": false,
					"physicsOn": false,
					"type": "Dynamic",
					"fixedAngle": false,
					"velocityX": 0,
					"velocityY": 0,
					"angularVelocity": 0,
					"density": 1,
					"friction": 0.5,
					"restitution": 0.5,
					"dampingLinear": 0,
					"dampingAngular": 0,
					"scriptList": [
						{
							"name": "Script_1",
							"nodeList": [
								{
									"type": "Collision",
									"parameters": {
										"tags": "player"
									},
									"nodeListTrue": [
										{
											"type": "Edit",
											"parameters": {
												"property": "coinsControler.coins",
												"value": "coinsControler.coins+1"
											}
										},
										{
											"type": "Delete",
											"parameters": {}
										}
									],
									"nodeListFalse": []
								}
							]
						}
					]
				},
				{
					"name": "Actor_12",
					"sleeping": false,
					"x": -360,
					"y": 200,
					"width": 24,
					"height": 20,
					"scaleX": 1,
					"scaleY": 1,
					"angle": 0,
					"screen": true,
					"collider": "Box",
					"tags": "",
					"spriteOn": true,
					"image": "LifeHearth_Full.png",
					"color": "#ffffff",
					"opacity": 1,
					"flipX": false,
					"flipY": false,
					"scrollX": 0,
					"scrollY": 0,
					"tileX": 1,
					"tileY": 1,
					"textOn": false,
					"text": "",
					"font": "Arial",
					"size": 30,
					"fill": "#000000",
					"style": "Normal",
					"align": "Center",
					"offsetX": 0,
					"offsetY": 0,
					"soundOn": false,
					"sound": "",
					"start": 0,
					"volume": 1,
					"pan": 0,
					"loop": false,
					"physicsOn": false,
					"type": "Dynamic",
					"fixedAngle": false,
					"velocityX": 0,
					"velocityY": 0,
					"angularVelocity": 0,
					"density": 1,
					"friction": 0.5,
					"restitution": 0.5,
					"dampingLinear": 0,
					"dampingAngular": 0,
					"scriptList": [
						{
							"name": "Script_1",
							"nodeList": [
								{
									"type": "Compare",
									"parameters": {
										"value_1": "Game.lives",
										"operation": "Less",
										"value_2": "1"
									},
									"nodeListTrue": [
										{
											"type": "Edit",
											"parameters": {
												"property": "Me.image",
												"value": "LifeHearth_Empty.png"
											}
										}
									],
									"nodeListFalse": []
								}
							]
						}
					]
				},
				{
					"name": "Actor_12_copy",
					"sleeping": false,
					"x": -320,
					"y": 200,
					"width": 24,
					"height": 20,
					"scaleX": 1,
					"scaleY": 1,
					"angle": 0,
					"screen": true,
					"collider": "Box",
					"tags": "",
					"spriteOn": true,
					"image": "LifeHearth_Full.png",
					"color": "#ffffff",
					"opacity": 1,
					"flipX": false,
					"flipY": false,
					"scrollX": 0,
					"scrollY": 0,
					"tileX": 1,
					"tileY": 1,
					"textOn": false,
					"text": "",
					"font": "Arial",
					"size": 30,
					"fill": "#000000",
					"style": "Normal",
					"align": "Center",
					"offsetX": 0,
					"offsetY": 0,
					"soundOn": false,
					"sound": "",
					"start": 0,
					"volume": 1,
					"pan": 0,
					"loop": false,
					"physicsOn": false,
					"type": "Dynamic",
					"fixedAngle": false,
					"velocityX": 0,
					"velocityY": 0,
					"angularVelocity": 0,
					"density": 1,
					"friction": 0.5,
					"restitution": 0.5,
					"dampingLinear": 0,
					"dampingAngular": 0,
					"scriptList": [
						{
							"name": "Script_1",
							"nodeList": [
								{
									"type": "Compare",
									"parameters": {
										"value_1": "Game.lives",
										"operation": "Less",
										"value_2": "2"
									},
									"nodeListTrue": [
										{
											"type": "Edit",
											"parameters": {
												"property": "Me.image",
												"value": "LifeHearth_Empty.png"
											}
										}
									],
									"nodeListFalse": []
								}
							]
						}
					]
				},
				{
					"name": "Actor_12_copy_2",
					"sleeping": false,
					"x": -280,
					"y": 200,
					"width": 24,
					"height": 20,
					"scaleX": 1,
					"scaleY": 1,
					"angle": 0,
					"screen": true,
					"collider": "Box",
					"tags": "",
					"spriteOn": true,
					"image": "LifeHearth_Full.png",
					"color": "#ffffff",
					"opacity": 1,
					"flipX": false,
					"flipY": false,
					"scrollX": 0,
					"scrollY": 0,
					"tileX": 1,
					"tileY": 1,
					"textOn": false,
					"text": "",
					"font": "Arial",
					"size": 30,
					"fill": "#000000",
					"style": "Normal",
					"align": "Center",
					"offsetX": 0,
					"offsetY": 0,
					"soundOn": false,
					"sound": "",
					"start": 0,
					"volume": 1,
					"pan": 0,
					"loop": false,
					"physicsOn": false,
					"type": "Dynamic",
					"fixedAngle": false,
					"velocityX": 0,
					"velocityY": 0,
					"angularVelocity": 0,
					"density": 1,
					"friction": 0.5,
					"restitution": 0.5,
					"dampingLinear": 0,
					"dampingAngular": 0,
					"scriptList": [
						{
							"name": "Script_1",
							"nodeList": [
								{
									"type": "Compare",
									"parameters": {
										"value_1": "Game.lives",
										"operation": "Less",
										"value_2": "3"
									},
									"nodeListTrue": [
										{
											"type": "Animate",
											"parameters": {
												"animation": "LifeHearth_Empty.png",
												"fps": "1"
											}
										}
									],
									"nodeListFalse": []
								}
							]
						}
					]
				},
				{
					"name": "Actor_13",
					"sleeping": false,
					"x": 370.52056531850263,
					"y": 200,
					"width": 21,
					"height": 21,
					"scaleX": 1,
					"scaleY": 1,
					"angle": 0,
					"screen": true,
					"collider": "Box",
					"tags": "",
					"spriteOn": true,
					"image": "CoinYellow.png",
					"color": "#ffffff",
					"opacity": 1,
					"flipX": false,
					"flipY": false,
					"scrollX": 0,
					"scrollY": 0,
					"tileX": 1,
					"tileY": 1,
					"textOn": false,
					"text": "",
					"font": "Arial",
					"size": 30,
					"fill": "#000000",
					"style": "Normal",
					"align": "Center",
					"offsetX": 0,
					"offsetY": 0,
					"soundOn": false,
					"sound": "",
					"start": 0,
					"volume": 1,
					"pan": 0,
					"loop": false,
					"physicsOn": false,
					"type": "Dynamic",
					"fixedAngle": false,
					"velocityX": 0,
					"velocityY": 0,
					"angularVelocity": 0,
					"density": 1,
					"friction": 0.5,
					"restitution": 0.5,
					"dampingLinear": 0,
					"dampingAngular": 0,
					"scriptList": []
				},
				{
					"name": "Actor_16",
					"sleeping": false,
					"x": -14.425256787509923,
					"y": -215.7526099261571,
					"width": 128,
					"height": 49,
					"scaleX": 1,
					"scaleY": 1,
					"angle": 0,
					"screen": false,
					"collider": "Box",
					"tags": "enemy",
					"spriteOn": true,
					"image": "SpearsUp_Gray.png",
					"color": "#ffffff",
					"opacity": 1,
					"flipX": false,
					"flipY": false,
					"scrollX": 0,
					"scrollY": 0,
					"tileX": 2,
					"tileY": 1,
					"textOn": false,
					"text": "",
					"font": "Arial",
					"size": 30,
					"fill": "#000000",
					"style": "Normal",
					"align": "Center",
					"offsetX": 0,
					"offsetY": 0,
					"soundOn": false,
					"sound": "",
					"start": 0,
					"volume": 1,
					"pan": 0,
					"loop": false,
					"physicsOn": false,
					"type": "Dynamic",
					"fixedAngle": false,
					"velocityX": 0,
					"velocityY": 0,
					"angularVelocity": 0,
					"density": 1,
					"friction": 0.5,
					"restitution": 0.5,
					"dampingLinear": 0,
					"dampingAngular": 0,
					"scriptList": []
				}
			]
		}
	],
	"lives": 3
}